prompt_generator/__init__.py
prompt_generator/run.py
prompt_generator/docs_prompt_generator/__init__.py
prompt_generator/docs_prompt_generator/main.py
prompt_generator/get_dir_structure/__init__.py
prompt_generator/get_dir_structure/main.py
prompt_generator/markdown_parser/__init__.py
prompt_generator/markdown_parser/main.py
prompt_generator/tasks_prompt_generator/__init__.py
prompt_generator/tasks_prompt_generator/main.py
prompt_generator/utils/__init__.py
prompt_generator/utils/file_utils.py
prompt_generator/utils/input_utils.py
prompt_generator/utils/print_utils.py
prompt_generator-0.4.0.dist-info/LICENSE
prompt_generator-0.4.0.dist-info/METADATA
prompt_generator-0.4.0.dist-info/WHEEL
prompt_generator-0.4.0.dist-info/entry_points.txt
prompt_generator-0.4.0.dist-info/top_level.txt
prompt_generator-0.4.0.dist-info/RECORD
