Metadata-Version: 2.1
Name: prompt-generator
Version: 0.4.0
Summary: Prompt Generator is a flexible and user-friendly package that offers customizable scripts for generating effective and context-aware prompts. These prompts can be used to guide the writing, improvement, and debugging of code.
Author: Vincenzo Cascone
License: MIT License
Project-URL: repository, https://github.com/vincenzocascone/prompt-generator
Classifier: Programming Language :: Python :: 3
Classifier: License :: OSI Approved :: MIT License
Classifier: Operating System :: OS Independent
Requires-Python: >=3.6
License-File: LICENSE
